foresight/__init__.py
foresight/__main__.py
foresight/__version__.py
foresight/calendar/__init__.py
foresight/calendar/credentials.json
foresight/calendar/event.py
foresight/calendar/google_calendar.py
foresight/console/__init__.py
foresight/console/application.py
foresight/console/command_loader.py
foresight/console/commands/__init__.py
foresight/console/commands/about.py
foresight/console/commands/command.py
foresight/console/commands/join.py
foresight/console/commands/peek.py
foresight/console/commands/update.py
foresight/factory.py
foresight/locations.py
foresight/tracking/__init__.py
foresight/tracking/harvest.py
foresight/tracking/harvest_credentials.py
foresight/tracking/project_task.py
foresight/utils/__init__.py
foresight/utils/appdirs.py
foresight/utils/auth.py
foresight/utils/zoom.py
foresight-0.3.2.dist-info/entry_points.txt
foresight-0.3.2.dist-info/LICENSE
foresight-0.3.2.dist-info/WHEEL
foresight-0.3.2.dist-info/METADATA
foresight-0.3.2.dist-info/RECORD
